midiutils/__init__.py
midiutils/midi_preprocessor.py
midiutils/types.py
midiutils_python-0.0.4.dist-info/licenses/LICENSE
midiutils_python-0.0.4.dist-info/METADATA
midiutils_python-0.0.4.dist-info/WHEEL
midiutils_python-0.0.4.dist-info/top_level.txt
midiutils_python-0.0.4.dist-info/RECORD
