Metadata-Version: 2.4
Name: midiutils-python
Version: 0.0.4
Summary: A collection of utilities for working with MIDI files built on top of mido.
Author-email: Oscar Andersson <oscar.966484@gmail.com>
License: MIT License
Project-URL: Source, https://github.com/pianoviz/midiutils
License-File: LICENSE
Requires-Dist: mido==1.3.2
Provides-Extra: dev
Requires-Dist: ruff; extra == "dev"
Requires-Dist: pytest; extra == "dev"
Dynamic: license-file
